ProgressPal/__init__.py
ProgressPal/cli.py
ProgressPal/ftrack.py
ProgressPal/ltrack.py
ProgressPal/weblog.py
ProgressPal/webapp/__init__.py
ProgressPal/webapp/webapp.py
ProgressPal/webapp/webapp_online_check.py
ProgressPal/webapp/static/favicon.ico
ProgressPal/webapp/static/css/functiontilestyle.css
ProgressPal/webapp/static/css/logtilestyle.css
ProgressPal/webapp/static/css/looptilestyle.css
ProgressPal/webapp/static/css/pagestyle.css
ProgressPal/webapp/static/css/settingsstyle.css
ProgressPal/webapp/static/css/themes.css
ProgressPal/webapp/static/js/functiontiles.js
ProgressPal/webapp/static/js/logtiles.js
ProgressPal/webapp/static/js/looptiles.js
ProgressPal/webapp/static/js/pageUI.js
ProgressPal/webapp/static/js/settings.js
ProgressPal/webapp/static/media/ProgressPalIcon.png
ProgressPal/webapp/static/media/ProgressPalMD.png
ProgressPal/webapp/static/settings/settings.json
ProgressPal/webapp/templates/index.html
ProgressPal-0.0.7.dist-info/LICENSE
ProgressPal-0.0.7.dist-info/METADATA
ProgressPal-0.0.7.dist-info/WHEEL
ProgressPal-0.0.7.dist-info/entry_points.txt
ProgressPal-0.0.7.dist-info/top_level.txt
ProgressPal-0.0.7.dist-info/RECORD
