Metadata-Version: 2.1
Name: ProgressPal
Version: 0.0.7
Summary: A decentralized iterable, function and log tracker
Home-page: https://github.com/levi2234/Progresspal
Author: Levi van Es
Author-email: levi2234@hotmail.com
Classifier: Programming Language :: Python :: 3
Classifier: License :: OSI Approved :: MIT License
Classifier: Operating System :: OS Independent
Requires-Python: >=3.9
License-File: LICENSE
Requires-Dist: Flask==3.0.3
Requires-Dist: Requests==2.32.3
Requires-Dist: numpy
Requires-Dist: waitress
Provides-Extra: dev
Requires-Dist: pytest-cov; extra == "dev"
